oemof/tools/__init__.py
oemof/tools/debugging.py
oemof/tools/economics.py
oemof/tools/logger.py
oemof.tools-0.4.3.dist-info/AUTHORS.rst
oemof.tools-0.4.3.dist-info/LICENSE
oemof.tools-0.4.3.dist-info/METADATA
oemof.tools-0.4.3.dist-info/WHEEL
oemof.tools-0.4.3.dist-info/top_level.txt
oemof.tools-0.4.3.dist-info/RECORD
