Metadata-Version: 2.1
Name: oemof.tools
Version: 0.4.3
Summary: Tiny tools of the oemof project.
Home-page: https://github.com/oemof/oemof-tools
Author: oemof-developer-group
Author-email: contact@oemof.org
License: MIT
Project-URL: Documentation, https://oemof-tools.readthedocs.io/
Project-URL: Changelog, https://oemof-tools.readthedocs.io/en/latest/changelog.html
Project-URL: Issue Tracker, https://github.com/oemof/oemof-tools/issues
Platform: UNKNOWN
Classifier: Development Status :: 5 - Production/Stable
Classifier: Intended Audience :: Developers
Classifier: License :: OSI Approved :: MIT License
Classifier: Operating System :: Unix
Classifier: Operating System :: POSIX
Classifier: Operating System :: Microsoft :: Windows
Classifier: Programming Language :: Python
Classifier: Programming Language :: Python :: 3
Classifier: Programming Language :: Python :: 3.8
Classifier: Programming Language :: Python :: 3.9
Classifier: Programming Language :: Python :: 3.10
Classifier: Programming Language :: Python :: Implementation :: CPython
Classifier: Topic :: Utilities
Requires-Python: >=3.8
License-File: LICENSE
License-File: AUTHORS.rst
Provides-Extra: dev
Requires-Dist: pytest ; extra == 'dev'
Requires-Dist: sphinx ; extra == 'dev'
Requires-Dist: sphinx-rtd-theme ; extra == 'dev'
